jsondbpy/__init__.py
jsondbpy/mysql.py
jsondbpy-1.1.1.dist-info/LICENSE
jsondbpy-1.1.1.dist-info/METADATA
jsondbpy-1.1.1.dist-info/WHEEL
jsondbpy-1.1.1.dist-info/top_level.txt
jsondbpy-1.1.1.dist-info/RECORD
