Metadata-Version: 2.1
Name: jsondbpy
Version: 1.1.1
Summary: Simple python local database
Author: Zoom Developer
Author-email: sa-mp12345@yandex.ru
Classifier: Programming Language :: Python :: 3
Classifier: License :: OSI Approved :: MIT License
Classifier: Operating System :: OS Independent
Requires-Python: >=3.6
License-File: LICENSE
